migcomparator/__init__.py
migcomparator/common/__init__.py
migcomparator/common/commonutils.py
migcomparator/common/stringutils.py
migcomparator/config/__init__.py
migcomparator/config/config.py
migcomparator/config/pd_spec_hive.py
migcomparator/config/pd_spec_mariadb.py
migcomparator/models/__init__.py
migcomparator/models/base_validator.py
migcomparator/models/datasource_table.py
migcomparator/models/pandas_validator.py
migcomparator/models/table.py
migcomparator/models/typeconverter.py
migcomparator/models/validation_result.py
migcomparator/query_sender/__init__.py
migcomparator/query_sender/connector.py
migcomparator/query_sender/decorator.py
migcomparator-1.0.3.dist-info/LICENSE.txt
migcomparator-1.0.3.dist-info/METADATA
migcomparator-1.0.3.dist-info/WHEEL
migcomparator-1.0.3.dist-info/top_level.txt
migcomparator-1.0.3.dist-info/RECORD
