Metadata-Version: 2.1
Name: migcomparator
Version: 1.0.3
Summary: Apache Hive and MariaDB(MySQL) compare library
Home-page: https://github.com/Altera520
Author: Gyojun An
Author-email: sencom1028@gmail.com
License: UNKNOWN
Platform: UNKNOWN
Classifier: Programming Language :: Python :: 3
Classifier: License :: OSI Approved :: MIT License
Classifier: Operating System :: OS Independent
Requires-Python: >=3.0
License-File: LICENSE.txt
Requires-Dist: impyla (==0.17.0)
Requires-Dist: pandas (>=1.1.5)
Requires-Dist: numpy (>=1.20.1)
Requires-Dist: PyMySQL (==1.0.2)
Requires-Dist: pandera (==0.8.0)
